mp3treesim/__init__.py
mp3treesim/__main__.py
mp3treesim/mp3treesim.py
mp3treesim-1.0.6.dist-info/LICENSE
mp3treesim-1.0.6.dist-info/METADATA
mp3treesim-1.0.6.dist-info/WHEEL
mp3treesim-1.0.6.dist-info/entry_points.txt
mp3treesim-1.0.6.dist-info/top_level.txt
mp3treesim-1.0.6.dist-info/RECORD
